Topsis_102003592/__init__.py
Topsis_102003592-0.3.dist-info/Licence.txt
Topsis_102003592-0.3.dist-info/METADATA
Topsis_102003592-0.3.dist-info/WHEEL
Topsis_102003592-0.3.dist-info/top_level.txt
Topsis_102003592-0.3.dist-info/RECORD
