Metadata-Version: 2.1
Name: Topsis-102003592
Version: 0.3
Summary: Evaluation of alternatives based on multiple criteria using TOPSIS method.
Home-page: UNKNOWN
Author: Bhavna Goyal
Author-email: bgoyal_be20@thapar.edu
License: UNKNOWN
Platform: UNKNOWN
Requires-Dist: pandas
